main.py
teams_import/__init__.py
teams_import/__main__.py
teams_import/shell.py
teams_import/templates/__init__.py
teams_import/templates/install-teams.ps1
teams_import/templates/__pycache__/__init__.cpython-38.pyc
teams_import-1.0.8.dev11.dist-info/METADATA
teams_import-1.0.8.dev11.dist-info/WHEEL
teams_import-1.0.8.dev11.dist-info/entry_points.txt
teams_import-1.0.8.dev11.dist-info/top_level.txt
teams_import-1.0.8.dev11.dist-info/RECORD
