Metadata-Version: 2.1
Name: teams-import
Version: 1.0.8.dev11
Summary: A command line tool for bulk importing students to MicrosoftTeams
Home-page: UNKNOWN
Author: Jake Renzella
Author-email: jake.renzella@deakin.edu.au
License: MIT
Platform: UNKNOWN
Requires-Dist: click
